mvgavg/__init__.py
mvgavg/main.py
mvgavg/mvgavg.py
mvgavg/version.py
mvgavg-0.1.0.dist-info/LICENSE.txt
mvgavg-0.1.0.dist-info/METADATA
mvgavg-0.1.0.dist-info/WHEEL
mvgavg-0.1.0.dist-info/top_level.txt
mvgavg-0.1.0.dist-info/RECORD
