Metadata-Version: 2.1
Name: mvgavg
Version: 0.1.0
Summary: Moving averages
Home-page: UNKNOWN
Author: NGeorgescu
Author-email: UNKNOWN
License: see LICENSE.txt
Keywords: mvgavg moving average movingaverage numpy python binning binned running run
Platform: UNKNOWN
Requires-Dist: numpy
